gcal_notifier/__init__.py
gcal_notifier/cli.py
gcal_notifier/config_reader.py
gcal_notifier/event_getter.py
gcal_notifier/event_loader.py
gcal_notifier/event_printer.py
gcal_notifier/event_reminder.py
gcal_notifier/event_saver.py
gcal_notifier/globals.py
gcal_notifier/main.py
gcal_notifier/resources/pop.wav
gcal_notifier/tabulate.py
gcal_notifier/utils.py
gcal_notifier-1.1.7.dist-info/LICENSE.md
gcal_notifier-1.1.7.dist-info/METADATA
gcal_notifier-1.1.7.dist-info/WHEEL
gcal_notifier-1.1.7.dist-info/entry_points.txt
gcal_notifier-1.1.7.dist-info/RECORD
