Metadata-Version: 2.3
Name: gcal_notifier
Version: 1.1.7
Summary: A simple and lightweight GoogleCalendar notifier for Linux
License: MIT
Author: Thales Nunes
Author-email: thalesaknunes22@gmail.com
Requires-Python: >=3.6.2,<4.0.0
Classifier: License :: OSI Approved :: MIT License
Classifier: Programming Language :: Python
Classifier: Programming Language :: Python :: 3
Classifier: Programming Language :: Python :: 3.7
Classifier: Programming Language :: Python :: 3.8
Classifier: Programming Language :: Python :: 3.9
Classifier: Programming Language :: Python :: 3.10
Classifier: Programming Language :: Python :: 3.11
Classifier: Programming Language :: Python :: 3.12
Classifier: Programming Language :: Python :: 3.13
Classifier: Programming Language :: Python :: 3.6
Requires-Dist: gcsa (>=1.2.0,<2.0.0)
Requires-Dist: simpleaudio (>=1.0.4,<2.0.0)
Project-URL: Repository, https://github.com/thalesnunes/gcal_notifier
